ltscaddstore/__init__.py
ltscaddstore/__version__.py
ltscaddstore/core.py
ltscaddstore-1.0.4.dist-info/LICENSE
ltscaddstore-1.0.4.dist-info/METADATA
ltscaddstore-1.0.4.dist-info/WHEEL
ltscaddstore-1.0.4.dist-info/top_level.txt
ltscaddstore-1.0.4.dist-info/RECORD
