Metadata-Version: 2.1
Name: ltscaddstore
Version: 1.0.4
Summary: Add an app store for Windows LTSC
Home-page: https://github.com/Goojoe/LTSC-ADD-Microsoft-Store
Author: Goojoe
Author-email: goojoer@gmail.com
License: MIT
Classifier: License :: OSI Approved :: MIT License
Classifier: Programming Language :: Python
Classifier: Programming Language :: Python :: 3
Classifier: Programming Language :: Python :: 3.7
Classifier: Programming Language :: Python :: Implementation :: CPython
Classifier: Programming Language :: Python :: Implementation :: PyPy
Requires-Python: >=3.7
License-File: LICENSE
Requires-Dist: requests
Requires-Dist: lxml
Requires-Dist: pyperclip
